[
    {
        "accuracy": 0.984,
        "batch": 64,
        "dropout": 0.3744098934678024,
        "duration": 118525346062,
        "lr": 0.11895442835110502,
        "momentum": 0.48186147778960553,
        "transform": "norm_299_flip",
        "uid": "6254017927c61679cc46126b8a625d58"
    },
    {
        "accuracy": 0.9255,
        "batch": 64,
        "dropout": 0.09575907569198239,
        "duration": 46659094538,
        "lr": 0.00955703267761971,
        "momentum": 0.7503999843772565,
        "transform": "echo_128_flip",
        "uid": "19ea3544212790ab8d3045ca76b58608"
    },
    {
        "accuracy": 0.9107,
        "batch": 256,
        "dropout": 0.0492670474397327,
        "duration": 342684888127,
        "lr": 0.039758778058374425,
        "momentum": 0.08326390982972487,
        "transform": "norm_512",
        "uid": "c67c0291b81a916180b6337f30035acf"
    },
    {
        "accuracy": 0.9085,
        "batch": 64,
        "dropout": 0.34373984416212594,
        "duration": 334423882644,
        "lr": 0.0007879476898537767,
        "momentum": 0.969057772347615,
        "transform": "echo_512",
        "uid": "587d9acf7aa413a41bc5d6dce9e572af"
    },
    {
        "accuracy": 0.7561,
        "batch": 8,
        "dropout": 0.1886341485031353,
        "duration": 70089056683,
        "lr": 0.000256617120068086,
        "momentum": 0.9479563361542902,
        "transform": "norm_flip",
        "uid": "e7931dfd17ce69e92078e95b708dd801"
    }
]