[
    {
        "accuracy": 0.5708,
        "batch": 8,
        "dropout": 0.12831140354943132,
        "duration": 92131296553,
        "lr": 0.015504942872982886,
        "momentum": 0.27022605860381155,
        "transform": "echo_64",
        "uid": "24e1a179a1cb55c8621c7e3fb0af2755"
    },
    {
        "accuracy": 0.5631,
        "batch": 8,
        "dropout": 0.06226544427243097,
        "duration": 298955537226,
        "lr": 0.05251002215132957,
        "momentum": 0.6639648578543522,
        "transform": "echo_256",
        "uid": "2745f3940a37ed524428f8e82d154d30"
    },
    {
        "accuracy": 0.4405,
        "batch": 128,
        "dropout": 0.052786954815838616,
        "duration": 322089341181,
        "lr": 0.13226377375943438,
        "momentum": 0.3330679784352035,
        "transform": "echo_256_flip",
        "uid": "f473ab40627945d195d0592d2a1fc898"
    },
    {
        "accuracy": 0.4261,
        "batch": 32,
        "dropout": 0.2994843367983827,
        "duration": 214339751182,
        "lr": 0.0011127439298893034,
        "momentum": 0.8576753281496183,
        "transform": "norm_256_flip",
        "uid": "ac81f5d7c548146f66375bd13e62e833"
    },
    {
        "accuracy": 0.4223,
        "batch": 32,
        "dropout": 0.07616605613373861,
        "duration": 66513043942,
        "lr": 0.008886827643845813,
        "momentum": 0.066624267865663,
        "transform": "norm_64_flip",
        "uid": "2f5129a5416ae72c9cfaf83ca4faae1d"
    },
    {
        "accuracy": 0.4062,
        "batch": 256,
        "dropout": 0.04736154671112003,
        "duration": 521279891511,
        "lr": 0.033035136052874225,
        "momentum": 0.35734548033554503,
        "transform": "norm_299",
        "uid": "ff1f596dd2ecd5794267b8ccf728f3b5"
    },
    {
        "accuracy": 0.1411,
        "batch": 128,
        "dropout": 0.34928584956663156,
        "duration": 56372076720,
        "lr": 0.5787365050716049,
        "momentum": 0.265709435105393,
        "transform": "norm_64",
        "uid": "49c135678fa14d0d26033238da07ddc3"
    }
]