[
    {
        "accuracy": 0.1086,
        "batch": 64,
        "dropout": 0.0001484654497627691,
        "duration": 134824460658,
        "lr": 0.583557275624991,
        "momentum": 0.6745015261009882,
        "transform": "echo_256",
        "uid": "5dab5eb19b2a6370b7ce2c622e0e1719"
    },
    {
        "accuracy": 0.1042,
        "batch": 4,
        "dropout": 0.29054282876825066,
        "duration": 68621595221,
        "lr": 0.3824758268727575,
        "momentum": 0.45198614645941126,
        "transform": "norm_128",
        "uid": "c174b9ec83b6bb077af67328e185785c"
    },
    {
        "accuracy": 0.0881,
        "batch": 4,
        "dropout": 0.24586351952255053,
        "duration": 167594179116,
        "lr": 0.0002934151410712519,
        "momentum": 0.8310270265147913,
        "transform": "norm_299_flip",
        "uid": "7b79c5bd499298cb3e4311af33071840"
    },
    {
        "accuracy": 0.0782,
        "batch": 2,
        "dropout": 0.43462006410520987,
        "duration": 87083147750,
        "lr": 0.0006109717596341678,
        "momentum": 0.8430010231656314,
        "transform": "norm_128",
        "uid": "93d5b5210e0de95ca9b7f17706f38d86"
    },
    {
        "accuracy": 0.0497,
        "batch": 8,
        "dropout": 0.438938425831744,
        "duration": 104217886675,
        "lr": 0.538153388534398,
        "momentum": 0.8212167795466027,
        "transform": "echo_299_flip",
        "uid": "e1a485ec85ad3a4ad15abf195f105ff8"
    },
    {
        "accuracy": 0.0274,
        "batch": 4,
        "dropout": 0.24372674703811503,
        "duration": 171707319707,
        "lr": 2.2492435617910295e-05,
        "momentum": 0.5572746433279385,
        "transform": "norm_299",
        "uid": "d02783e910323f33f48aeb70bfb91952"
    }
]