[
    {
        "accuracy": 0.1642,
        "batch": 8,
        "dropout": 0.4791094939916973,
        "duration": 113752344024,
        "lr": 0.026430714038980802,
        "momentum": 0.47424690877707354,
        "transform": "echo_299",
        "uid": "2f036a6124bee646d484a05bd2926414"
    },
    {
        "accuracy": 0.16,
        "batch": 2,
        "dropout": 0.25603243169566337,
        "duration": 272127080313,
        "lr": 0.0004104525081281002,
        "momentum": 0.9490474525198639,
        "transform": "norm_299",
        "uid": "f94ffb4c90cd651b0f500cdb96fcfa44"
    },
    {
        "accuracy": 0.1246,
        "batch": 2,
        "dropout": 0.07952361618835602,
        "duration": 273959760959,
        "lr": 0.009335269791211982,
        "momentum": 0.15365734434961476,
        "transform": "echo_256",
        "uid": "5b26a5a0535e8d2c3b92e750a9466a03"
    },
    {
        "accuracy": 0.078,
        "batch": 512,
        "dropout": 0.045087110896116944,
        "duration": 102775209400,
        "lr": 0.07615350864360293,
        "momentum": 0.7069946522711473,
        "transform": "norm_256",
        "uid": "23fc9cc752e3f32aed691619dcdd7301"
    },
    {
        "accuracy": 0.0148,
        "batch": 64,
        "dropout": 0.2542048758069738,
        "duration": 11071470953,
        "lr": 0.005355554267321857,
        "momentum": 0.7258189752992675,
        "transform": "norm_32",
        "uid": "0135c01ea06dc83cee052e6f6b6a1aab"
    },
    {
        "accuracy": 0.0121,
        "batch": 512,
        "dropout": 0.44131237270790263,
        "duration": 15551368183,
        "lr": 0.029704928472314304,
        "momentum": 0.869396536437205,
        "transform": "norm_64",
        "uid": "97c0a8917b95fd4e6de2cf3873027ab1"
    }
]