[
    {
        "accuracy": 0.9572688107404068,
        "batch": 8,
        "dropout": 0.1741002964628678,
        "duration": 306056600449,
        "lr": 0.0012231002863469101,
        "momentum": 0.6256581125039243,
        "transform": "norm_64_flip",
        "uid": "37c5510805b6fdef07796cb1cb3968d1"
    },
    {
        "accuracy": 0.613515679791604,
        "batch": 64,
        "dropout": 0.17113280036921757,
        "duration": 486875913853,
        "lr": 0.0016887566660042683,
        "momentum": 0.56532187721103,
        "transform": "echo_256",
        "uid": "035f1760de0a5157d9cdce421a018f2c"
    },
    {
        "accuracy": 0.613515679791604,
        "batch": 32,
        "dropout": 0.06564462216131328,
        "duration": 289937327137,
        "lr": 0.5080179523788898,
        "momentum": 0.2547864714530794,
        "transform": "norm_128",
        "uid": "1c147a4a7fb39f091fd224f8dc2bb1e7"
    },
    {
        "accuracy": 0.613515679791604,
        "batch": 512,
        "dropout": 0.07977850162969585,
        "duration": 597213846130,
        "lr": 0.005682029001019878,
        "momentum": 0.14873283265513493,
        "transform": "norm_256_flip",
        "uid": "9e7dad59a4a53ed8318d928bcf75452f"
    },
    {
        "accuracy": 0.613515679791604,
        "batch": 128,
        "dropout": 0.3959310422559556,
        "duration": 193641489663,
        "lr": 0.0002343447174242529,
        "momentum": 0.09483730911544697,
        "transform": "norm_32",
        "uid": "cfc05fe33c91234721875510c23d3a2f"
    },
    {
        "accuracy": 0.613515679791604,
        "batch": 512,
        "dropout": 0.37584432968038156,
        "duration": 339998229013,
        "lr": 0.005468483580592054,
        "momentum": 0.06702024514802252,
        "transform": "norm_flip",
        "uid": "2a5194276b6d5227d45a17ef3a495e0e"
    }
]