[
    {
        "accuracy": 0.9808,
        "batch": 1024,
        "dropout": 0.2092967757174542,
        "duration": 57308263464,
        "lr": 0.14013435850647687,
        "momentum": 0.9240969873137034,
        "transform": "echo_64",
        "uid": "f225052ce74d99c428cd47b58c103a97"
    },
    {
        "accuracy": 0.9732,
        "batch": 128,
        "dropout": 0.47552097810811633,
        "duration": 282727059814,
        "lr": 0.011575505354773157,
        "momentum": 0.7179324965210009,
        "transform": "norm_256_flip",
        "uid": "0cbfd3aeb0cbc9b05bdcc21de4ed00ee"
    },
    {
        "accuracy": 0.948,
        "batch": 32,
        "dropout": 0.45732966268296377,
        "duration": 118105592822,
        "lr": 0.3625854174283145,
        "momentum": 0.3704447255998975,
        "transform": "echo_128_flip",
        "uid": "a348feb745a26fd7b5fe49605bc697fb"
    },
    {
        "accuracy": 0.8806,
        "batch": 128,
        "dropout": 0.07991136145070366,
        "duration": 69813603572,
        "lr": 0.08011340312599453,
        "momentum": 0.5624294421198655,
        "transform": "norm_flip",
        "uid": "e67aa5962f734c539815104a91275386"
    },
    {
        "accuracy": 0.8545,
        "batch": 128,
        "dropout": 0.041419681948636544,
        "duration": 61247028081,
        "lr": 0.2784283688368505,
        "momentum": 0.755607341054588,
        "transform": "norm",
        "uid": "5f466227b47dfb7822355b54c46dcc91"
    }
]