[
    {
        "accuracy": 0.7427,
        "batch": 16,
        "dropout": 0.40072659402850164,
        "duration": 246360031918,
        "lr": 0.06285020926440199,
        "momentum": 0.39787818684982446,
        "transform": "norm_299",
        "uid": "6b87859c886f9321445e31da9e4ceb76"
    },
    {
        "accuracy": 0.7355,
        "batch": 2,
        "dropout": 0.33714967804675217,
        "duration": 550320606300,
        "lr": 0.01870451605113057,
        "momentum": 0.06414165826140539,
        "transform": "norm_256",
        "uid": "8d23d0bae83cdaa367afa2c3b4480078"
    },
    {
        "accuracy": 0.7158,
        "batch": 128,
        "dropout": 0.44177596352895543,
        "duration": 863577412837,
        "lr": 0.07886751483573742,
        "momentum": 0.7694378004464122,
        "transform": "norm_512_flip",
        "uid": "63bcf715eb3568db44cf0c9b78639389"
    },
    {
        "accuracy": 0.6007,
        "batch": 64,
        "dropout": 0.33438791861996453,
        "duration": 808429854164,
        "lr": 0.0017349003019892977,
        "momentum": 0.9727759403162731,
        "transform": "norm_512_flip",
        "uid": "d02d6c2d075e732be38b15088c29f666"
    },
    {
        "accuracy": 0.55,
        "batch": 8,
        "dropout": 0.2529942727206481,
        "duration": 637663240186,
        "lr": 0.014802298239954739,
        "momentum": 0.3840455103107768,
        "transform": "echo_512",
        "uid": "e8aa04ccccd25a6a576293317aabe2b2"
    },
    {
        "accuracy": 0.2329,
        "batch": 4,
        "dropout": 0.45392987751713476,
        "duration": 433044914446,
        "lr": 0.19848120121985652,
        "momentum": 0.07895853946697173,
        "transform": "norm_299_flip",
        "uid": "260e4f50a2f51290ce5bd515cbc9bfcd"
    }
]