[
    {
        "accuracy": 0.49910828025477705,
        "batch": 16,
        "dropout": 0.16682531947399548,
        "duration": 142351904905,
        "lr": 0.05013557002579861,
        "momentum": 0.7054710865076936,
        "transform": "norm_32_flip",
        "uid": "3381c0ad019a6dff0546b542d6c6556c"
    },
    {
        "accuracy": 0.3819108280254777,
        "batch": 32,
        "dropout": 0.08598312510436623,
        "duration": 196687649729,
        "lr": 0.00209771944686626,
        "momentum": 0.8746427382975865,
        "transform": "norm_256_flip",
        "uid": "69b1c88b3c5d9be303ef10489f250e6f"
    },
    {
        "accuracy": 0.36789808917197453,
        "batch": 16,
        "dropout": 0.13766000457123512,
        "duration": 158069358872,
        "lr": 0.33905525855751706,
        "momentum": 0.07275447060327278,
        "transform": "norm_128",
        "uid": "2456f39e5ac1c13bcc159a216e9df0d6"
    },
    {
        "accuracy": 0.3444585987261147,
        "batch": 1,
        "dropout": 0.18088911094089716,
        "duration": 378842860857,
        "lr": 0.0020703049887323146,
        "momentum": 0.014882817128466397,
        "transform": "echo_512_flip",
        "uid": "ed5e9b2e0076df773b65e2f6fb422642"
    },
    {
        "accuracy": 0.329171974522293,
        "batch": 8,
        "dropout": 0.4022667190718308,
        "duration": 155750691426,
        "lr": 0.006735403212843165,
        "momentum": 0.9631246463708161,
        "transform": "norm_64_flip",
        "uid": "7b0a8863f7ee498852d5f21b93774414"
    }
]