[
    {
        "accuracy": 0.9083,
        "batch": 8,
        "duration": 1989887200530,
        "lr": 0.0019749773277064667,
        "momentum": 0.25712075605478524,
        "transform": "norm_512_flip",
        "uid": "f7d129555c694212d2764d483ecbae29"
    },
    {
        "accuracy": 0.7619,
        "batch": 16,
        "duration": 551313900366,
        "lr": 8.971357579062746e-05,
        "momentum": 0.15632985452535808,
        "transform": "norm_256",
        "uid": "6555105921e4175cf699fb7543f23add"
    }
]