[
    {
        "accuracy": 0.9902,
        "batch": 2,
        "dropout": 0.16240432593730575,
        "duration": 283162008041,
        "lr": 0.018904373657663773,
        "momentum": 0.10917876035223484,
        "transform": "echo_64",
        "uid": "e6383cc1c69025b7735cc17ca3444b49"
    },
    {
        "accuracy": 0.9883,
        "batch": 8,
        "dropout": 0.2419005027181822,
        "duration": 73683783163,
        "lr": 0.001768442313953962,
        "momentum": 0.9091142411198927,
        "transform": "norm_64",
        "uid": "a627924a2ecea7e5ded9e4113389a2c2"
    },
    {
        "accuracy": 0.9733,
        "batch": 8,
        "dropout": 0.44855391571492176,
        "duration": 116182251835,
        "lr": 0.18434280145493837,
        "momentum": 0.13800363419622919,
        "transform": "norm_128_flip",
        "uid": "3477b0b3afa3bad0504ce1935409e7c5"
    },
    {
        "accuracy": 0.9719,
        "batch": 16,
        "dropout": 0.1918820967498734,
        "duration": 87799416620,
        "lr": 0.0035503403979744224,
        "momentum": 0.530827383718148,
        "transform": "norm_128",
        "uid": "6302f5ef6c3df47f7f12648c02852947"
    },
    {
        "accuracy": 0.9685,
        "batch": 16,
        "dropout": 0.4944450807621387,
        "duration": 89188189988,
        "lr": 0.002455394807302386,
        "momentum": 0.5645079392051384,
        "transform": "norm_128",
        "uid": "d4b896002c80bc66db696bb28f2d5bc8"
    },
    {
        "accuracy": 0.6364,
        "batch": 4,
        "dropout": 0.38457358769404093,
        "duration": 162971796588,
        "lr": 9.610279681642896e-05,
        "momentum": 0.39335863589713926,
        "transform": "norm_128",
        "uid": "2f9e2ff45071f69f9fced36dfaf31bc9"
    }
]