{"data_mtime":1705381322,"dep_lines":[1,3,4,5,6,7,1,1,1,1,1,1,1,1,1,1,1],"dep_prios":[5,10,10,10,10,10,5,30,30,30,30,30,30,30,30,30,30],"dependencies":["iot_devices","subprocess","platform","time","threading","requests","builtins","_typeshed","abc","http","http.cookiejar","os","requests.auth","requests.cookies","requests.models","typing","typing_extensions"],"hash":"9322a15b1934be6f7924f4302d5079e5811af5b2352e824ae44a2986d453a0b1","id":"iot_devices.iot_devices.devices.servermonitor","ignore_all":false,"interface_hash":"5141f12af1f7369b2d3d64c6457b56f46c2e2056b4ef205b6b8e8c68441b4442","mtime":1705381233,"options":{"allow_redefinition":false,"allow_untyped_globals":false,"always_false":[],"always_true":[],"bazel":false,"check_untyped_defs":false,"disable_bytearray_promotion":false,"disable_error_code":[],"disable_memoryview_promotion":false,"disabled_error_codes":[],"disallow_any_decorated":false,"disallow_any_explicit":false,"disallow_any_expr":false,"disallow_any_generics":false,"disallow_any_unimported":false,"disallow_incomplete_defs":false,"disallow_subclassing_any":false,"disallow_untyped_calls":false,"disallow_untyped_decorators":false,"disallow_untyped_defs":false,"enable_error_code":[],"enabled_error_codes":[],"extra_checks":false,"follow_imports":"normal","follow_imports_for_stubs":false,"ignore_errors":false,"ignore_missing_imports":false,"implicit_optional":false,"implicit_reexport":true,"local_partial_types":false,"mypyc":false,"new_type_inference":false,"platform":"linux","plugins":[],"strict_concatenate":false,"strict_equality":false,"strict_optional":true,"warn_no_return":true,"warn_return_any":false,"warn_unreachable":false,"warn_unused_ignores":false},"path":"/home/daniel/Projects/iot_devices/iot_devices/devices/servermonitor/__init__.py","plugin_data":null,"size":2372,"suppressed":[],"version_id":"1.6.1"}