[
    {
        "accuracy": 0.2904,
        "batch": 2,
        "dropout": 0.28190070055776706,
        "duration": 575897256393,
        "lr": 0.012632264619923141,
        "momentum": 0.1855847906877277,
        "transform": "norm_flip",
        "uid": "8566a2115cbd5035fff4f279741ed5b3"
    },
    {
        "accuracy": 0.2852,
        "batch": 8,
        "dropout": 0.3184768742765092,
        "duration": 165037643364,
        "lr": 0.021507413042335072,
        "momentum": 0.2456211848354637,
        "transform": "echo_128",
        "uid": "a6cffd99ed656a50d1e6f7cabb703f6e"
    },
    {
        "accuracy": 0.206,
        "batch": 32,
        "dropout": 0.3351806131272108,
        "duration": 241397029678,
        "lr": 0.009760496656693273,
        "momentum": 0.8107196364639281,
        "transform": "echo_299_flip",
        "uid": "f74a9636c3fef267c703a77a0c29ed57"
    },
    {
        "accuracy": 0.1762,
        "batch": 16,
        "dropout": 0.20107685824182608,
        "duration": 753421476535,
        "lr": 0.00285457067105812,
        "momentum": 0.7940162410277966,
        "transform": "norm_512",
        "uid": "f8ba4755888d8a8c872c4f402232442e"
    },
    {
        "accuracy": 0.1209,
        "batch": 8,
        "dropout": 0.27480505169549607,
        "duration": 164646952896,
        "lr": 0.0037589541847133545,
        "momentum": 0.3032188155475667,
        "transform": "norm_64_flip",
        "uid": "e8c932ba01e4889c447ae218ed704205"
    }
]