[
    {
        "accuracy": 0.454,
        "batch": 32,
        "dropout": 0.3330522784597946,
        "duration": 35380939085,
        "lr": 0.06633331868452012,
        "momentum": 0.7506157589158331,
        "transform": "echo_256",
        "uid": "f56f33cd32140e48bec255e9a3311c7c"
    },
    {
        "accuracy": 0.4431,
        "batch": 2,
        "dropout": 0.1484875592896322,
        "duration": 196748259363,
        "lr": 0.008153231724754175,
        "momentum": 0.04519806862954168,
        "transform": "norm_512_flip",
        "uid": "3b056ca4b29b744f99af6c3c9d151e1f"
    },
    {
        "accuracy": 0.4349,
        "batch": 128,
        "dropout": 0.04533544188332922,
        "duration": 10669830029,
        "lr": 0.06960276137835612,
        "momentum": 0.8040932188364058,
        "transform": "norm_64",
        "uid": "bb675c5cd2f44ecefed60d55a22c939f"
    },
    {
        "accuracy": 0.2919,
        "batch": 8,
        "dropout": 0.06983254115892268,
        "duration": 193882903848,
        "lr": 0.0024066072817906753,
        "momentum": 0.47925169987645777,
        "transform": "echo_512_flip",
        "uid": "05890376ba40a2fd8a2b44b9fabc57db"
    },
    {
        "accuracy": 0.2026,
        "batch": 512,
        "dropout": 0.2572100880690484,
        "duration": 59874150124,
        "lr": 0.08326396774383908,
        "momentum": 0.6886837697253415,
        "transform": "echo_299_flip",
        "uid": "3fe151502054953fc68715e8df15042f"
    },
    {
        "accuracy": 0.1435,
        "batch": 16,
        "dropout": 0.3108201195814214,
        "duration": 48749193491,
        "lr": 0.002480232552236364,
        "momentum": 0.33216180389308847,
        "transform": "echo_299_flip",
        "uid": "9a2a94d5c905cee181f35db746122326"
    }
]