[
    {
        "accuracy": 0.1756,
        "batch": 4,
        "dropout": 0.10646141622179506,
        "duration": 185986233069,
        "lr": 0.007186281992177564,
        "momentum": 0.3057042125952708,
        "transform": "norm_256",
        "uid": "ecaeb42d05443b2a963be7eca50f1375"
    },
    {
        "accuracy": 0.1324,
        "batch": 32,
        "dropout": 0.11837589440530644,
        "duration": 155947545789,
        "lr": 0.022854736648242634,
        "momentum": 0.07000160780391096,
        "transform": "norm_256",
        "uid": "0fd332db8613542183142417aaae8790"
    },
    {
        "accuracy": 0.0882,
        "batch": 32,
        "dropout": 0.37181707190928376,
        "duration": 211886815607,
        "lr": 0.027924763036442476,
        "momentum": 0.4322912575578557,
        "transform": "echo_299",
        "uid": "bc53e70236e1ba72fa90cc38354c1518"
    }
]