[
    {
        "accuracy": 0.6197,
        "batch": 64,
        "dropout": 0.08722092210538762,
        "duration": 38239162954,
        "lr": 0.012348361402442637,
        "momentum": 0.9724491597107299,
        "transform": "norm_64",
        "uid": "64c8d2ef585fcf6e4c9051dce4d9e2de"
    },
    {
        "accuracy": 0.4235,
        "batch": 2,
        "dropout": 0.028707223471636123,
        "duration": 667951734662,
        "lr": 0.0011317354987480687,
        "momentum": 0.10447897541286977,
        "transform": "echo_299",
        "uid": "52631df11c6301829dc2d2b4bc21db2c"
    },
    {
        "accuracy": 0.4226,
        "batch": 2,
        "dropout": 0.07906833039592198,
        "duration": 602335440355,
        "lr": 0.0006908673871270563,
        "momentum": 0.24164790219139398,
        "transform": "norm_128_flip",
        "uid": "4b21f79782386a29dbe08173f06c2640"
    },
    {
        "accuracy": 0.377,
        "batch": 512,
        "dropout": 0.19564968087459927,
        "duration": 80195569390,
        "lr": 0.03828945064802754,
        "momentum": 0.4221993735341256,
        "transform": "norm_128",
        "uid": "82588549a03415e32a0e3ebc6fb9899c"
    },
    {
        "accuracy": 0.322,
        "batch": 1024,
        "dropout": 0.26647470617539026,
        "duration": 282548207039,
        "lr": 0.2249467828025602,
        "momentum": 0.28564829810170367,
        "transform": "norm_256",
        "uid": "67a6ce7570255001e4b780f47e7d0326"
    }
]