[
    {
        "accuracy": 0.9897,
        "batch": 32,
        "dropout": 0.24961610250171012,
        "duration": 131213002396,
        "lr": 0.033786327425551176,
        "momentum": 0.09845877522131974,
        "transform": "norm_128",
        "uid": "ee2caad76dd899de2b1fde3a507be6be"
    },
    {
        "accuracy": 0.988,
        "batch": 64,
        "dropout": 0.2660972145415814,
        "duration": 249945805021,
        "lr": 0.5269463903393633,
        "momentum": 0.05929473017859355,
        "transform": "echo_256_flip",
        "uid": "581bc4634549f648410d99ede42fd90b"
    },
    {
        "accuracy": 0.9544,
        "batch": 64,
        "dropout": 0.27689951551058956,
        "duration": 81691056367,
        "lr": 0.008361164087627335,
        "momentum": 0.18490879616068012,
        "transform": "echo_128",
        "uid": "aa55ceace797330044807d91adf8826d"
    },
    {
        "accuracy": 0.9529,
        "batch": 32,
        "dropout": 0.4542423870229228,
        "duration": 51590476680,
        "lr": 0.15814451108109814,
        "momentum": 0.7738048448836247,
        "transform": "echo",
        "uid": "29fb6497b5082db6ca72c9abdd0c1df7"
    },
    {
        "accuracy": 0.1908,
        "batch": 8,
        "dropout": 0.08747028817323471,
        "duration": 173410295896,
        "lr": 3.601382454855701e-05,
        "momentum": 0.46936764622859983,
        "transform": "norm_32",
        "uid": "08693e881d8b9187892951da297fe98e"
    }
]