[
    {
        "accuracy": 0.989,
        "batch": 64,
        "dropout": 0.2486045627429591,
        "duration": 554698071398,
        "lr": 0.06731487107262443,
        "momentum": 0.4166722345495777,
        "transform": "norm_512",
        "uid": "59a37e17aacceb013372e0dc2d12d51b"
    },
    {
        "accuracy": 0.9884,
        "batch": 64,
        "dropout": 0.4915299278082194,
        "duration": 528847278810,
        "lr": 0.030937854162426445,
        "momentum": 0.8464045082061188,
        "transform": "echo_512",
        "uid": "60bc407699fb4c68781185f1d4d5755b"
    },
    {
        "accuracy": 0.9782,
        "batch": 256,
        "dropout": 0.11363828095289213,
        "duration": 50322064516,
        "lr": 0.031998176742911395,
        "momentum": 0.5874280589056878,
        "transform": "norm_64",
        "uid": "f41891764d75b035ba6bb7b700e85614"
    },
    {
        "accuracy": 0.9143,
        "batch": 256,
        "dropout": 0.2318300285092555,
        "duration": 45692263778,
        "lr": 0.13275511530250375,
        "momentum": 0.3056032889384024,
        "transform": "echo_128_flip",
        "uid": "90cb46c8b1e0095e7c4bc6d8cf7fa2fd"
    },
    {
        "accuracy": 0.9109,
        "batch": 256,
        "dropout": 0.2915805433460188,
        "duration": 544433644665,
        "lr": 0.2978813421561665,
        "momentum": 0.1594821977471449,
        "transform": "echo_512_flip",
        "uid": "8a623fca596b6cdfa9b66abd51213915"
    }
]