[
    {
        "accuracy": 0.974,
        "batch": 256,
        "dropout": 0.37638267870816505,
        "duration": 38145437149,
        "lr": 0.22261393310571886,
        "momentum": 0.9279562564589886,
        "transform": "norm_128",
        "uid": "26b5a9c048db78c2fd120ab74c59f4c8"
    },
    {
        "accuracy": 0.9687,
        "batch": 128,
        "dropout": 0.19140712019009243,
        "duration": 155880824906,
        "lr": 0.009595410351342232,
        "momentum": 0.748965937298258,
        "transform": "norm_299_flip",
        "uid": "2004703a689dc03589b4b17037c08740"
    },
    {
        "accuracy": 0.9511,
        "batch": 8,
        "dropout": 0.15746286445101876,
        "duration": 277248525484,
        "lr": 0.005319963370452188,
        "momentum": 0.010119071535065527,
        "transform": "norm_299_flip",
        "uid": "17ea8ccf072c50d9b24e0e80b64e8e60"
    },
    {
        "accuracy": 0.8542,
        "batch": 4,
        "dropout": 0.4795996075738296,
        "duration": 708746394468,
        "lr": 0.00013290462337685734,
        "momentum": 0.8946186253441095,
        "transform": "norm_512",
        "uid": "788bb5a98b3ddf91c2b7f556adc5402a"
    },
    {
        "accuracy": 0.8417,
        "batch": 4,
        "dropout": 0.3116381136590224,
        "duration": 406688568812,
        "lr": 0.0002859265150576886,
        "momentum": 0.8294572238815933,
        "transform": "echo_299_flip",
        "uid": "e9947d26d1548c55f2079f568b3cad62"
    }
]