[
    {
        "accuracy": 0.6036,
        "batch": 32,
        "dropout": 0.4913252589459408,
        "duration": 38585563293,
        "lr": 0.01918272342658264,
        "momentum": 0.3936529882914771,
        "transform": "norm_64_flip",
        "uid": "b30a6608f8c8536235c7d887918615e3"
    },
    {
        "accuracy": 0.5373,
        "batch": 64,
        "dropout": 0.4029422302570929,
        "duration": 160767892943,
        "lr": 0.021817664051262824,
        "momentum": 0.2013709643126117,
        "transform": "norm_256_flip",
        "uid": "8eb9f09d38d4ec9cb4b425c968ecfc90"
    },
    {
        "accuracy": 0.5276,
        "batch": 4,
        "dropout": 0.2531095447142153,
        "duration": 300695499173,
        "lr": 0.12006924121630182,
        "momentum": 0.3035863045573759,
        "transform": "norm_256",
        "uid": "13edf1753645443c45045b26125be741"
    },
    {
        "accuracy": 0.5183,
        "batch": 8,
        "dropout": 0.04860685691451566,
        "duration": 127540102141,
        "lr": 0.01502847323201596,
        "momentum": 0.10489011144252336,
        "transform": "norm",
        "uid": "21bb56b8dd1296841df87b3b8a2e3555"
    },
    {
        "accuracy": 0.4926,
        "batch": 128,
        "dropout": 0.08521964049870495,
        "duration": 20580883028,
        "lr": 0.03015469430837785,
        "momentum": 0.7179789321812458,
        "transform": "norm_32",
        "uid": "f9480c20a3cadcb7ec0a7ae5dff69f15"
    }
]