[
    {
        "accuracy": 0.613515679791604,
        "batch": 16,
        "dropout": 0.15918084694162854,
        "duration": 376054301630,
        "lr": 0.5628031838887901,
        "momentum": 0.6420131240423688,
        "transform": "norm_64",
        "uid": "e892307b05f5e60afd4b442c5d3a6f89"
    },
    {
        "accuracy": 0.613515679791604,
        "batch": 128,
        "dropout": 0.3518075963266847,
        "duration": 371481941588,
        "lr": 3.5484305253722264e-05,
        "momentum": 0.7068994600005392,
        "transform": "norm_64",
        "uid": "718eaaba87f0bf7f59096f8d2e45cefc"
    },
    {
        "accuracy": 0.613515679791604,
        "batch": 1024,
        "dropout": 0.05471066614288811,
        "duration": 933728599854,
        "lr": 0.0020290183112675266,
        "momentum": 0.24215009594575077,
        "transform": "echo_256",
        "uid": "2a1146363051d3205a6dfcf43cd60e0f"
    },
    {
        "accuracy": 0.613515679791604,
        "batch": 64,
        "dropout": 0.26624031096027095,
        "duration": 439321226546,
        "lr": 2.8287258081438916e-05,
        "momentum": 0.6865670068773418,
        "transform": "echo_128",
        "uid": "dc14a6f43c6ce628c63e029b8f878c97"
    },
    {
        "accuracy": 0.613515679791604,
        "batch": 4096,
        "dropout": 0.35403955833493767,
        "duration": 636193517763,
        "lr": 2.0696961122942003e-05,
        "momentum": 0.3623151284996715,
        "transform": "echo",
        "uid": "b3c9446ac999da49e29feb4b26d38f5f"
    },
    {
        "accuracy": 0.613515679791604,
        "batch": 128,
        "dropout": 0.22188289990069376,
        "duration": 448600440114,
        "lr": 0.0002929621978757773,
        "momentum": 0.5394353203181166,
        "transform": "echo_128_flip",
        "uid": "1a49f68efff7c4253a6d0239e0210bd8"
    }
]