[
    {
        "accuracy": 0.5935,
        "batch": 16,
        "dropout": 0.2,
        "duration": 159142482229,
        "epoch": 5,
        "lr": 0.01,
        "momentum": 0.9,
        "transform": "norm_flip",
        "uid": "9777bd2579ece9cc5a05d9aab5b950d7"
    },
    {
        "accuracy": 0.4619,
        "batch": 64,
        "dropout": 0.46688293750678894,
        "duration": 1110155821598,
        "lr": 0.011987616892362172,
        "momentum": 0.466730870283374,
        "transform": "norm_64_flip",
        "uid": "e2d95956d653f1c449cacfbbb1eb75ac"
    }
]