[
    {
        "accuracy": 0.3095541401273885,
        "batch": 2,
        "dropout": 0.4475274062829368,
        "duration": 34903238248,
        "lr": 0.003919081070914144,
        "momentum": 0.8164237859874166,
        "transform": "norm_64_flip",
        "uid": "3d9a531a18d87b4093691d39db62cf04"
    },
    {
        "accuracy": 0.30038216560509556,
        "batch": 16,
        "dropout": 0.12386824061414953,
        "duration": 30168063191,
        "lr": 0.0966493411256473,
        "momentum": 0.5192524999944238,
        "transform": "norm_128",
        "uid": "7fbc15659ecc9788a2ce1703c7842629"
    },
    {
        "accuracy": 0.20203821656050955,
        "batch": 32,
        "dropout": 0.20617389224761584,
        "duration": 40131368523,
        "lr": 0.051458704039082745,
        "momentum": 0.9435902156924644,
        "transform": "norm_299",
        "uid": "ff90d47e9225f57bd3c1fbdefabdb6d4"
    },
    {
        "accuracy": 0.17401273885350318,
        "batch": 4,
        "dropout": 0.3489686522665958,
        "duration": 30145761479,
        "lr": 0.02611541205242452,
        "momentum": 0.04776894262245701,
        "transform": "echo_64",
        "uid": "4f8969341abbe861f29102b3b63a07d9"
    },
    {
        "accuracy": 0.14343949044585988,
        "batch": 1,
        "dropout": 0.4441882835971741,
        "duration": 61533966217,
        "lr": 2.0385674615828856e-05,
        "momentum": 0.9879202097535302,
        "transform": "echo_299",
        "uid": "f5cf6b6d225aad38f6ab5f1c935bc559"
    },
    {
        "accuracy": 0.12509554140127388,
        "batch": 32,
        "dropout": 0.14058693261916583,
        "duration": 35580005396,
        "lr": 0.1874243913885747,
        "momentum": 0.3836566861968834,
        "transform": "echo_256_flip",
        "uid": "74eb7411adafe0021f22a22d3a0407d1"
    }
]